aig_service/test/__init__.py
aig_service/test/service.py
aig_service/test1/__init__.py
aig_service/test1/service.py
aig_test-0.0.1.dist-info/METADATA
aig_test-0.0.1.dist-info/WHEEL
aig_test-0.0.1.dist-info/top_level.txt
aig_test-0.0.1.dist-info/RECORD
