Metadata-Version: 2.1
Name: aig-test
Version: 0.0.1
Summary: test-test
